Metadata-Version: 2.4
Name: dbt-pip-audit
Version: 2.10.0
Summary: DBT tool for scanning Python environments for known vulnerabilities
Author-email: Mouhajer Zaouali <mouhajer.zaouali@digital.trade.gov.uk>
Requires-Python: >=3.10
Classifier: Development Status :: 5 - Production/Stable
Classifier: Intended Audience :: Developers
Classifier: License :: OSI Approved :: Apache Software License
Classifier: Programming Language :: Python :: 3 :: Only
Classifier: Programming Language :: Python :: 3
Classifier: Programming Language :: Python :: 3.10
Classifier: Programming Language :: Python :: 3.11
Classifier: Programming Language :: Python :: 3.12
Classifier: Programming Language :: Python :: 3.13
Classifier: Programming Language :: Python :: 3.14
Classifier: Topic :: Security
License-File: LICENSE
Requires-Dist: CacheControl[filecache] >= 0.13.0
Requires-Dist: cyclonedx-python-lib >= 5,< 12
Requires-Dist: packaging>=23.0.0
Requires-Dist: pip-api>=0.0.28
Requires-Dist: pip-requirements-parser>=32.0.0
Requires-Dist: requests >= 2.31.0
Requires-Dist: rich >= 12.4
Requires-Dist: tomli >= 2.2.1
Requires-Dist: tomli-w >= 1.2.0
Requires-Dist: platformdirs >= 4.2.0
Requires-Dist: coverage[toml] ~= 7.0, != 7.3.3 ; extra == "cov"
Requires-Dist: build ; extra == "dev"
Requires-Dist: pip-audit[doc, test, lint] ; extra == "dev"
Requires-Dist: pdoc ; extra == "doc"
Requires-Dist: ruff >= 0.11 ; extra == "lint"
Requires-Dist: interrogate ~= 1.6 ; extra == "lint"
Requires-Dist: mypy ; extra == "lint"
Requires-Dist: types-requests ; extra == "lint"
Requires-Dist: types-toml ; extra == "lint"
Requires-Dist: pretend ; extra == "test"
Requires-Dist: pytest ; extra == "test"
Requires-Dist: pip-audit[cov] ; extra == "test"
Project-URL: Homepage, https://pypi.org/project/dbt-pip-audit/
Project-URL: Issues, https://github.com/uktrade/pip-audit/issues
Project-URL: Source, https://github.com/uktrade/pip-audit
Provides-Extra: cov
Provides-Extra: dev
Provides-Extra: doc
Provides-Extra: lint
Provides-Extra: test
